Metadata-Version: 2.1
Name: snakedict
Version: 1.0.0
Summary: Keep your dict keys PEP 8 compliant.
Author: ZeroIntensity
Author-email: <zintensitydev@gmail.com>
License: MIT
Keywords: python,pep 8,dicts
Platform: UNKNOWN
Classifier: Programming Language :: Python :: 3.6
Classifier: Programming Language :: Python :: 3.7
Classifier: Programming Language :: Python :: 3.8
Classifier: Programming Language :: Python :: 3.9
Classifier: Programming Language :: Python :: 3.10
Classifier: Programming Language :: Python :: 3.11
License-File: LICENSE
